pomw/__init__.py
pomw/__version__.py
pomw/config.py
pomw/console/__init__.py
pomw/console/application.py
pomw/exceptions.py
pomw/model/__init__.py
pomw/model/entries.py
pomw/model/entry.py
pomw/model/interval.py
pomw/model/pomodoro.py
pomw/tasks.py
pomw/tdt.py
pomw-0.1.0.dist-info/entry_points.txt
pomw-0.1.0.dist-info/LICENSE
pomw-0.1.0.dist-info/WHEEL
pomw-0.1.0.dist-info/METADATA
pomw-0.1.0.dist-info/RECORD
